{
  "pathPrefix": "/",
  "examplePageUrl": "http://localhost:3000",
  "createdDate": 1618890594274,
  "defaultQuery": [],
  "showAbTests": true,
  "requiredTargets": [],
  "designerVersion": 1,
  "autoTracked": true,
  "fields": [
    {
      "disallowRemove": false,
      "helperText": "",
      "copyOnAdd": true,
      "required": false,
      "showIf": "",
      "onChange": "",
      "simpleTextOnly": false,
      "noPhotoPicker": false,
      "enum": [
        "base",
        "tailwind",
        "swiss",
        "future",
        "deep",
        "system",
        "funk",
        "sketchy",
        "roboto",
        "tosh",
        "bulma",
        "polaris"
      ],
      "model": "",
      "@type": "@builder.io/core:Field",
      "advanced": false,
      "mandatory": false,
      "hideFromUI": false,
      "hidden": false,
      "showTemplatePicker": true,
      "broadcast": false,
      "hideFromFieldsEditor": false,
      "autoFocus": false,
      "name": "theme",
      "type": "text",
      "subFields": [],
      "permissionsRequiredToEdit": "",
      "bubble": false
    },
    {
      "disallowRemove": false,
      "@type": "@builder.io/core:Field",
      "showIf": "",
      "advanced": false,
      "permissionsRequiredToEdit": "",
      "hidden": false,
      "type": "object",
      "showTemplatePicker": true,
      "simpleTextOnly": false,
      "hideFromFieldsEditor": false,
      "hideFromUI": false,
      "broadcast": false,
      "autoFocus": false,
      "onChange": "",
      "noPhotoPicker": false,
      "bubble": false,
      "subFields": [
        {
          "hideFromFieldsEditor": false,
          "name": "text",
          "subFields": [],
          "permissionsRequiredToEdit": "",
          "required": false,
          "onChange": "",
          "model": "",
          "showIf": "",
          "hidden": false,
          "mandatory": false,
          "copyOnAdd": true,
          "advanced": false,
          "broadcast": false,
          "hideFromUI": false,
          "type": "color",
          "disallowRemove": false,
          "bubble": false,
          "autoFocus": false,
          "noPhotoPicker": false,
          "showTemplatePicker": true,
          "simpleTextOnly": false,
          "helperText": "",
          "@type": "@builder.io/core:Field"
        },
        {
          "model": "",
          "disallowRemove": false,
          "showTemplatePicker": true,
          "showIf": "",
          "copyOnAdd": true,
          "advanced": false,
          "hideFromFieldsEditor": false,
          "type": "color",
          "required": false,
          "onChange": "",
          "subFields": [],
          "hidden": false,
          "autoFocus": false,
          "hideFromUI": false,
          "mandatory": false,
          "permissionsRequiredToEdit": "",
          "helperText": "",
          "bubble": false,
          "simpleTextOnly": false,
          "noPhotoPicker": false,
          "broadcast": false,
          "@type": "@builder.io/core:Field",
          "name": "background"
        },
        {
          "autoFocus": false,
          "noPhotoPicker": false,
          "hidden": false,
          "disallowRemove": false,
          "type": "color",
          "simpleTextOnly": false,
          "showTemplatePicker": true,
          "advanced": false,
          "copyOnAdd": true,
          "name": "primary",
          "onChange": "",
          "bubble": false,
          "required": false,
          "mandatory": false,
          "broadcast": false,
          "subFields": [],
          "helperText": "",
          "showIf": "",
          "hideFromFieldsEditor": false,
          "@type": "@builder.io/core:Field",
          "hideFromUI": false,
          "model": "",
          "permissionsRequiredToEdit": ""
        },
        {
          "autoFocus": false,
          "subFields": [],
          "hideFromFieldsEditor": false,
          "model": "",
          "showTemplatePicker": true,
          "mandatory": false,
          "permissionsRequiredToEdit": "",
          "showIf": "",
          "simpleTextOnly": false,
          "required": false,
          "@type": "@builder.io/core:Field",
          "copyOnAdd": true,
          "broadcast": false,
          "noPhotoPicker": false,
          "onChange": "",
          "hidden": false,
          "disallowRemove": false,
          "type": "color",
          "helperText": "",
          "advanced": false,
          "bubble": false,
          "name": "secondary",
          "hideFromUI": false
        },
        {
          "simpleTextOnly": false,
          "autoFocus": false,
          "showTemplatePicker": true,
          "showIf": "",
          "name": "muted",
          "mandatory": false,
          "onChange": "",
          "broadcast": false,
          "model": "",
          "type": "color",
          "noPhotoPicker": false,
          "hidden": false,
          "hideFromFieldsEditor": false,
          "advanced": false,
          "subFields": [],
          "copyOnAdd": true,
          "disallowRemove": false,
          "bubble": false,
          "required": false,
          "helperText": "",
          "hideFromUI": false,
          "@type": "@builder.io/core:Field",
          "permissionsRequiredToEdit": ""
        }
      ],
      "helperText": "",
      "required": false,
      "name": "colorOverrides",
      "model": "",
      "defaultValue": {},
      "mandatory": false,
      "copyOnAdd": true
    },
    {
      "noPhotoPicker": false,
      "type": "object",
      "bubble": false,
      "showTemplatePicker": true,
      "hideFromUI": false,
      "hidden": false,
      "hideFromFieldsEditor": false,
      "required": false,
      "advanced": false,
      "simpleTextOnly": false,
      "subFields": [
        {
          "name": "title",
          "model": "",
          "advanced": false,
          "required": false,
          "permissionsRequiredToEdit": "",
          "bubble": false,
          "onChange": "",
          "mandatory": false,
          "simpleTextOnly": false,
          "helperText": "Default SEO title",
          "showIf": "",
          "showTemplatePicker": true,
          "disallowRemove": false,
          "hideFromUI": false,
          "noPhotoPicker": false,
          "hidden": false,
          "copyOnAdd": true,
          "autoFocus": false,
          "hideFromFieldsEditor": false,
          "subFields": [],
          "@type": "@builder.io/core:Field",
          "defaultValue": "Builder.io + Next.js + Shopify Demo",
          "type": "text",
          "broadcast": false
        },
        {
          "mandatory": false,
          "broadcast": false,
          "onChange": "",
          "hideFromFieldsEditor": false,
          "type": "text",
          "helperText": "%s is where the page title will be",
          "permissionsRequiredToEdit": "",
          "required": false,
          "advanced": false,
          "name": "titleTemplate",
          "@type": "@builder.io/core:Field",
          "hidden": false,
          "model": "",
          "defaultValue": "%s - Headless Demo",
          "noPhotoPicker": false,
          "bubble": false,
          "copyOnAdd": true,
          "simpleTextOnly": false,
          "hideFromUI": false,
          "disallowRemove": false,
          "showIf": "",
          "autoFocus": false,
          "subFields": [],
          "showTemplatePicker": true
        },
        {
          "name": "description",
          "hideFromFieldsEditor": false,
          "simpleTextOnly": false,
          "permissionsRequiredToEdit": "",
          "autoFocus": false,
          "showIf": "",
          "showTemplatePicker": true,
          "disallowRemove": false,
          "type": "text",
          "defaultValue": "A starter kit demo store for using headless shopify with Builder.io ->  https://github.com/BuilderIO/nextjs-shopify",
          "copyOnAdd": true,
          "hideFromUI": false,
          "onChange": "",
          "broadcast": false,
          "bubble": false,
          "model": "",
          "subFields": [],
          "mandatory": false,
          "advanced": false,
          "noPhotoPicker": false,
          "hidden": false,
          "helperText": "Default description text for site pages ( SEO)",
          "@type": "@builder.io/core:Field",
          "required": false
        },
        {
          "autoFocus": false,
          "hideFromFieldsEditor": false,
          "onChange": "",
          "model": "",
          "copyOnAdd": true,
          "type": "map",
          "showIf": "",
          "required": false,
          "advanced": false,
          "@type": "@builder.io/core:Field",
          "mandatory": false,
          "hideFromUI": false,
          "bubble": false,
          "disallowRemove": false,
          "hidden": false,
          "name": "openGraph",
          "permissionsRequiredToEdit": "",
          "noPhotoPicker": false,
          "showTemplatePicker": true,
          "defaultValue": {
            "type": "website",
            "site_name": "Builder.io + Next.js + Shopify Demo",
            "locale": "en_IE",
            "url": "https://github.com/BuilderIO/nextjs-shopify"
          },
          "broadcast": false,
          "subFields": [],
          "simpleTextOnly": false,
          "helperText": "Open graph map"
        }
      ],
      "defaultValue": {
        "openGraph": {
          "site_name": "Builder.io + Next.js Demo",
          "type": "website",
          "locale": "en_IE",
          "url": "https://example.com"
        },
        "title": "Builder.io + Next.js Demo",
        "titleTemplate": "%s - Demo",
        "description": "A demo for using theme ui with Builder.io"
      },
      "permissionsRequiredToEdit": "",
      "showIf": "",
      "helperText": "",
      "broadcast": false,
      "disallowRemove": false,
      "name": "siteInformation",
      "model": "",
      "@type": "@builder.io/core:Field",
      "copyOnAdd": true,
      "mandatory": false,
      "autoFocus": false,
      "onChange": ""
    }
  ],
  "getSchemaFromPage": false,
  "individualEmbed": false,
  "subType": "",
  "publicReadable": true,
  "isPage": false,
  "archived": false,
  "name": "theme",
  "useQueryParamTargetingClientSide": false,
  "showScheduling": true,
  "sendToMongoDb": true,
  "lastUpdateBy": null,
  "strictPrivateRead": false,
  "id": "75d7d923971f422e816a647dc70c3666",
  "hideOptions": false,
  "helperText": "",
  "hideFromUI": false,
  "allowMetrics": true,
  "sendToElasticSearch": false,
  "injectWcPosition": "",
  "singleton": false,
  "showMetrics": true,
  "repeatable": false,
  "publicWritable": false,
  "kind": "data",
  "schema": {},
  "allowTests": true,
  "allowHeatmap": true,
  "webhooks": [],
  "@originId": "db2a380dda804d25a678f3c1252e2267",
  "componentsOnlyMode": false,
  "showTargeting": true,
  "apiGenerated": true,
  "allowBuiltInComponents": true,
  "injectWcAt": "",
  "bigData": false,
  "hooks": {},
  "strictPrivateWrite": false,
  "hidden": false
}
